pydoc_fork/__about__.py
pydoc_fork/__init__.py
pydoc_fork/__main__.py
pydoc_fork/commands.py
pydoc_fork/inspector/__init__.py
pydoc_fork/inspector/custom_types.py
pydoc_fork/inspector/module_utils.py
pydoc_fork/inspector/path_utils.py
pydoc_fork/inspector/utils.py
pydoc_fork/reporter/__init__.py
pydoc_fork/reporter/format_class.py
pydoc_fork/reporter/format_data.py
pydoc_fork/reporter/format_module.py
pydoc_fork/reporter/format_other.py
pydoc_fork/reporter/format_page.py
pydoc_fork/reporter/format_routine.py
pydoc_fork/reporter/formatter_html.py
pydoc_fork/reporter/html_repr_class.py
pydoc_fork/reporter/inline_styles.py
pydoc_fork/reporter/jinja_code.py
pydoc_fork/reporter/rst_support.py
pydoc_fork/reporter/string_utils.py
pydoc_fork/settings.py
pydoc_fork/templates/heading.jinja2
pydoc_fork/templates/page.jinja2
pydoc_fork/templates/section.jinja2
pydoc_fork/templates/style.css
pydoc_fork-3.3.0.dist-info/LICENSE
pydoc_fork-3.3.0.dist-info/METADATA
pydoc_fork-3.3.0.dist-info/WHEEL
pydoc_fork-3.3.0.dist-info/entry_points.txt
pydoc_fork-3.3.0.dist-info/RECORD
