Metadata-Version: 2.1
Name: pydoc_fork
Version: 3.3.0
Summary: Fork of cpython's pydoc module to do just html document generation
Home-page: https://github.com/matthewdeanmartin/pydoc_fork
License: MIT
Keywords: pydoc,html documentation
Author: Matthew Martin
Author-email: matthewdeanmartin@gmail.com
Requires-Python: >=3.8,<4
Classifier: Development Status :: 5 - Production/Stable
Classifier: Intended Audience :: Developers
Classifier: License :: OSI Approved :: MIT License
Classifier: Operating System :: OS Independent
Classifier: Programming Language :: Python
Classifier: Programming Language :: Python :: 3
Classifier: Programming Language :: Python :: 3.8
Classifier: Programming Language :: Python :: 3.9
Classifier: Programming Language :: Python :: 3.10
Classifier: Programming Language :: Python :: 3.11
Classifier: Programming Language :: Python :: 3.12
Classifier: Programming Language :: Python :: 3.7
Requires-Dist: docopt-ng (>=0.9.0,<1)
Requires-Dist: docutils (>=0.20.1,<1)
Requires-Dist: jinja2 (>=3.1.3,<4)
Requires-Dist: markdown (>=3.5.2,<4)
Requires-Dist: tomli (>=2.0.1,<3)
Requires-Dist: typing_extensions
Project-URL: Bug Tracker, https://github.com/matthewdeanmartin/pydoc_fork/issues
Project-URL: Change Log, https://github.com/matthewdeanmartin/pydoc_fork/blob/main/CHANGES.md
Project-URL: Documentation, https://github.com/matthewdeanmartin/pydoc_fork
Project-URL: Repository, https://github.com/matthewdeanmartin/pydoc_fork
